pact_methodology/__init__.py
pact_methodology/assurance/__init__.py
pact_methodology/assurance/assurance.py
pact_methodology/carbon_footprint/__init__.py
pact_methodology/carbon_footprint/biogenic_accounting_methodology.py
pact_methodology/carbon_footprint/carbon_footprint.py
pact_methodology/carbon_footprint/characterization_factors.py
pact_methodology/carbon_footprint/cross_sectoral_standard.py
pact_methodology/carbon_footprint/cross_sectoral_standard_set.py
pact_methodology/carbon_footprint/declared_unit.py
pact_methodology/carbon_footprint/emission_factor_ds.py
pact_methodology/carbon_footprint/emission_factor_ds_set.py
pact_methodology/carbon_footprint/geographical_scope.py
pact_methodology/carbon_footprint/product_or_sector_specific_rule.py
pact_methodology/carbon_footprint/product_or_sector_specific_rule_operator.py
pact_methodology/carbon_footprint/product_or_sector_specific_rule_set.py
pact_methodology/carbon_footprint/reference_period.py
pact_methodology/carbon_footprint/region_or_subregion.py
pact_methodology/data_model_extension/__init__.py
pact_methodology/data_model_extension/data_model_extension.py
pact_methodology/data_quality_indicators/__init__.py
pact_methodology/data_quality_indicators/data_quality_indicators.py
pact_methodology/data_quality_indicators/data_quality_rating.py
pact_methodology/datetime.py
pact_methodology/exceptions.py
pact_methodology/product_footprint/__init__.py
pact_methodology/product_footprint/company_id_list.py
pact_methodology/product_footprint/cpc.py
pact_methodology/product_footprint/cpc_v21.csv
pact_methodology/product_footprint/id.py
pact_methodology/product_footprint/product_footprint.py
pact_methodology/product_footprint/product_id_list.py
pact_methodology/product_footprint/status.py
pact_methodology/product_footprint/validity_period.py
pact_methodology/product_footprint/version.py
pact_methodology/urn.py
pact_methodology-0.0.3.dist-info/LICENSE
pact_methodology-0.0.3.dist-info/METADATA
pact_methodology-0.0.3.dist-info/WHEEL
pact_methodology-0.0.3.dist-info/RECORD
