Metadata-Version: 2.1
Name: pact-methodology
Version: 0.0.3
Summary: 
Author: JohnVonNeumann
Author-email: louis@zerotwentyfifty.com
Requires-Python: >=3.11,<4.0
Classifier: Programming Language :: Python :: 3
Classifier: Programming Language :: Python :: 3.11
Classifier: Programming Language :: Python :: 3.12
Requires-Dist: casregnum (>=1.0.1,<2.0.0)
Requires-Dist: pycountry (>=23.12.11,<24.0.0)
Requires-Dist: python-dateutil (>=2.9.0.post0,<3.0.0)
Requires-Dist: urnparse (>=0.2.1,<0.3.0)
